jdutimer/__init__.py
jdutimer/display.py
jdutimer/timer.py
jdutimer-0.2.1.data/scripts/jdutimer
jdutimer-0.2.1.dist-info/LICENSE
jdutimer-0.2.1.dist-info/METADATA
jdutimer-0.2.1.dist-info/WHEEL
jdutimer-0.2.1.dist-info/top_level.txt
jdutimer-0.2.1.dist-info/RECORD
