Metadata-Version: 2.1
Name: jdutimer
Version: 0.2.1
Summary: A usefull timer package to measure and pack functions' execution time.
Home-page: https://github.com/jeandemeusy/jdu_timer
Author: Jean Demeusy
Author-email: dev.jdu@gmail.com
License: UNKNOWN
Platform: UNKNOWN
Classifier: Programming Language :: Python :: 3
Classifier: License :: OSI Approved :: MIT License
Classifier: Operating System :: OS Independent
